conf/bumblebees.yml
conf/honeybees.yml
conf/hym/Acep.yml
conf/hym/Ador.yml
conf/hym/Aech.yml
conf/hym/Aflo.yml
conf/hym/Amel.yml
conf/hym/Bimp.yml
conf/hym/Bter.yml
conf/hym/Cbir.yml
conf/hym/Cflo.yml
conf/hym/Dnov.yml
conf/hym/Dqua.yml
conf/hym/Emex.yml
conf/hym/Hlab.yml
conf/hym/Hsal.yml
conf/hym/Lalb.yml
conf/hym/Lhum.yml
conf/hym/Mqua.yml
conf/hym/Mrot.yml
conf/hym/Nvit.yml
conf/hym/Pbar.yml
conf/hym/Pcan.yml
conf/hym/Pdom.yml
conf/hym/Sinv.yml
conf/modorg/Atha.yml
conf/modorg/Bdis.yml
conf/modorg/Btau.yml
conf/modorg/Cele.yml
conf/modorg/Dmel.yml
conf/modorg/Drer.yml
conf/modorg/Mmus.yml
conf/modorg/Pfal.yml
conf/modorg/Scer.yml
conf/modorg/Tcas.yml
conf/modorg/Xtro.yml
genhub/__init__.py
genhub/_version.py
genhub/beebase.py
genhub/conf.py
genhub/crg.py
genhub/download.py
genhub/exons.py
genhub/fasta.py
genhub/genomedb.py
genhub/iloci.py
genhub/mrnas.py
genhub/ncbi_flybase.py
genhub/pdom.py
genhub/proteins.py
genhub/refseq.py
genhub/stats.py
genhub-0.1.1.data/scripts/genhub-build.py
genhub-0.1.1.data/scripts/genhub-filens.py
genhub-0.1.1.data/scripts/genhub-fix-trna.py
genhub-0.1.1.data/scripts/genhub-format-gff3.py
genhub-0.1.1.data/scripts/genhub-namedup.py
genhub-0.1.1.data/scripts/genhub-stats.py
genhub-0.1.1.dist-info/DESCRIPTION.rst
genhub-0.1.1.dist-info/METADATA
genhub-0.1.1.dist-info/RECORD
genhub-0.1.1.dist-info/WHEEL
genhub-0.1.1.dist-info/metadata.json
genhub-0.1.1.dist-info/top_level.txt
