Metadata-Version: 2.0
Name: genhub
Version: 0.1.1
Summary: Collect and pre-process annotated genome assemblies
Home-page: http://github.com/standage/genhub
Author: Daniel Standage
Author-email: daniel.standage@gmail.com
License: BSD-3
Platform: UNKNOWN
Requires-Dist: pycurl
Requires-Dist: pyyaml
